xbee900_HIT/__init__.py
xbee900_HIT/packet.py
xbee900_HIT/xbee.py
xbee900_HIT-0.1.2.dist-info/LICENSE.txt
xbee900_HIT-0.1.2.dist-info/METADATA
xbee900_HIT-0.1.2.dist-info/WHEEL
xbee900_HIT-0.1.2.dist-info/top_level.txt
xbee900_HIT-0.1.2.dist-info/RECORD
