Metadata-Version: 2.1
Name: xbee900-HIT
Version: 0.1.2
Summary: A small package to send/receive fragmented data with XBee 900
Author-email: Zhiyuan Cao <caozhiyuan@stu.hit.edu.cn>
License: Copyright (c) <year> <copyright holders>
Project-URL: Homepage, https://gitee.com/czy_hit/xbee
Project-URL: Bug Tracker, https://gitee.com/czy_hit/xbee
Classifier: Programming Language :: Python :: 3
Classifier: Operating System :: OS Independent
Requires-Python: >=3.8
License-File: LICENSE.txt
Requires-Dist: digi-xbee (==1.4.1)
